Remarker-0.0.9.dist-info/DESCRIPTION.rst
Remarker-0.0.9.dist-info/METADATA
Remarker-0.0.9.dist-info/RECORD
Remarker-0.0.9.dist-info/WHEEL
Remarker-0.0.9.dist-info/entry_points.txt
Remarker-0.0.9.dist-info/metadata.json
Remarker-0.0.9.dist-info/top_level.txt
remarker/__init__.py
remarker/_version.py
remarker/cli.py
remarker/presentation.py
remarker/templates/default.css
remarker/templates/default.html
